{
  "grid-layout" : {
    "mapping" : {
      "column" : {
        "padding" : {
          "value" : "{space.0.value}"
        }
      },
      "row" : {
        "gap" : {
          "value" : "{space.4.value}"
        }
      }
    },
    "appearances" : {
      "condensed" : {
        "mapping" : {
          "width" : {
            "value" : "100%"
          },
          "row" : {
            "gap" : {
              "value" : "{space.0.value}"
            }
          },
          "column" : {
            "padding" : {
              "value" : "{space.0.value}"
            }
          }
        }
      }
    },
    "meta" : {
      "appearances" : {
        "condensed" : {
          "source" : "user"
        }
      }
    }
  }
}
